MANIFEST.in
setup.cfg
setup.py
iis_bridge/__init__.py
iis_bridge/config.py
iis_bridge/isapi.py
iis_bridge/load_gen.py
iis_bridge/mem.py
iis_bridge/mon.py
iis_bridge/pool.py
iis_bridge/site.py
iis_bridge.egg-info/PKG-INFO
iis_bridge.egg-info/SOURCES.txt
iis_bridge.egg-info/dependency_links.txt
iis_bridge.egg-info/not-zip-safe
iis_bridge.egg-info/requires.txt
iis_bridge.egg-info/top_level.txt
iis_bridge/templates/template1.html
test/test.py