Metadata-Version: 1.1
Name: iis-bridge
Version: 1.8
Summary: an iis management tool for windows
Home-page: https://github.com/kouroshparsa/iis_bridge
Author: Kourosh Parsa
Author-email: kouroshtheking@gmail.com
License: GNU
Download-URL: https://github.com/kouroshparsa/iis_bridge/packages/1.8
Platform: windows
Classifier: Environment :: Web Environment
Classifier: Operating System :: Microsoft :: Windows
Classifier: Programming Language :: Python
Classifier: Programming Language :: Python :: 2.7
